LICENSE
README.md
pyproject.toml
setup.cfg
unat/__init__.py
unat.egg-info/PKG-INFO
unat.egg-info/SOURCES.txt
unat.egg-info/dependency_links.txt
unat.egg-info/not-zip-safe
unat.egg-info/requires.txt
unat.egg-info/top_level.txt