Metadata-Version: 2.1
Name: unat
Version: 0.0.0.dev1
Summary: Uncertainty Analysis Tools
Author: José Mário da Silva Filho
Author-email: mariofilho281@gmail.com
License: MIT
Keywords: uncertainty,measurement,monte-carlo,experiments
Classifier: Programming Language :: Python :: 3
Classifier: Intended Audience :: Science/Research
Requires-Python: >=3.10
License-File: LICENSE
Requires-Dist: numpy
Requires-Dist: scipy
Requires-Dist: matplotlib
